setup.py
xesai/__init__.py
xesai/version.py
xesai.egg-info/PKG-INFO
xesai.egg-info/SOURCES.txt
xesai.egg-info/dependency_links.txt
xesai.egg-info/requires.txt
xesai.egg-info/top_level.txt
xesai/chat/__init__.py
xesai/chat/robot.py
xesai/chat/sseclient.py