Metadata-Version: 2.1
Name: xesai
Version: 0.0.1
Summary: 学而思AI库
Home-page: https://code.xueersi.com
Author: xes
